llm_hacker_news.py
llm_hacker_news-0.1.1.dist-info/licenses/LICENSE
llm_hacker_news-0.1.1.dist-info/METADATA
llm_hacker_news-0.1.1.dist-info/WHEEL
llm_hacker_news-0.1.1.dist-info/entry_points.txt
llm_hacker_news-0.1.1.dist-info/top_level.txt
llm_hacker_news-0.1.1.dist-info/RECORD
