Metadata-Version: 2.4
Name: llm-hacker-news
Version: 0.1.1
Summary: LLM plugin for pulling content from Hacker News
Author: Simon Willison
License-Expression: Apache-2.0
Project-URL: Homepage, https://github.com/simonw/llm-hacker-news
Project-URL: Changelog, https://github.com/simonw/llm-hacker-news/releases
Project-URL: Issues, https://github.com/simonw/llm-hacker-news/issues
Project-URL: CI, https://github.com/simonw/llm-hacker-news/actions
Requires-Python: >=3.9
License-File: LICENSE
Requires-Dist: llm>=0.24
Requires-Dist: httpx
Provides-Extra: test
Requires-Dist: pytest; extra == "test"
Requires-Dist: pytest-httpx; extra == "test"
Dynamic: license-file
